[
  {
    "questionId": 0,
    "questionText": "באיזה שנה הוקמה מדינת ישראל?",
    "answers": ["1948", "1983", "1890", "1939"],
    "rightAnswerIndex": 0
  },
  {
    "questionId": 1,
    "questionText": "מי הוא ראש הממשלה שנקבר בנגב?",
    "answers": ["יצחק רבין", "אריאל שרון", "דוד בן גוריון", "לוי אשכול"],
    "rightAnswerIndex": 2
  },
  {
    "questionId": 2,
    "questionText": "מהם 3 ערכי היסוד במסמך רוח צה״ל?",
    "answers": [
      "הגנת המדינה, אזרחיה ותושביה, אהבת המולדת ונאמנות למדינה, כבוד האדם",
      "רעות, משמעת, הגנת המדינה, אזרחיה ותושביה",
      "אהבת המולדת ונאמנות למדינה, טוהר הנשק, שליחות",
      "כבוד האדם, דוגמה אישית, מקצועיות"
    ],
    "rightAnswerIndex": 0
  },
  {
    "questionId": 3,
    "questionText": "איזו עיר ישראלית נקראה בעבר \"אום רשרש\"?",
    "answers": ["באר שבע", "אילת", "טבריה", "תל אביב"],
    "rightAnswerIndex": 1
  },
  {
    "questionId": 4,
    "questionText": "באיזה מבצע הונף דגל הדיו?",
    "answers": [
      "מבצע עופרת יצוקה",
      "מבצע אנטבה",
      "מבצע עובדה",
      "מבצע צוק איתן"
    ],
    "rightAnswerIndex": 2
  },
  {
    "questionId": 5,
    "questionText": "על שם מי קרוי מחנה מגן סיירים?",
    "answers": [
      "ע״ש האלוף קלמן מגן",
      "המגן של בר כוכבא",
      "רב אלוף יעקב דורי",
      "ע״ש חיילי חטיבת גולני שהיו המגן של חטיבת הנחל"
    ],
    "rightAnswerIndex": 0
  },
  {
    "questionId": 6,
    "questionText": "מדוע האזור נקרא \"בקעת סיירים\"? ",
    "answers": [
      "סיירים - חיה שהייתה נפוצה בערבה אך הוכחדה",
      "ע״ש הסיירים שסיירו באזור",
      "ע״ש העקבות שהשאירו המסתננים ממצרים"
    ],
    "rightAnswerIndex": 1
  },
  {
    "questionId": 7,
    "questionText": "מהו שמו של הגדוד המעורב הראשון?",
    "answers": ["קרקל", "414", "אריות הירדן", "47"],
    "rightAnswerIndex": 0
  },
  {
    "questionId": 8,
    "questionText": "לכל גדוד בצבא יש מספר, 33 הוא מספרו של גדוד קרקל. מה הוא מייצג?",
    "answers": [
      "33 הקילומטרים שקיימים בין המרחק של הגדוד מירושלים",
      "מייצג את 33 לוחמות הפלמ״ח אשר נפלו בקרבות בתש״ח",
      "ע״ש 33 לוחמים שפרצו במבצע עובדה"
    ],
    "rightAnswerIndex": 1
  },
  {
    "expPageId": 0,
    "text": "זוהי לומדה הבאה לתרגל את הכשירות הערכית ואת הידע וההתמצאות שלכם במורשת החיל"
  },
  {
    "expPageId": 1,
    "headline": "מחנה מגן סיירים",
    "text": "כחלק מהסכם השלום עם מצרים הושלם בשנת 1982 פינוי חצי האי סיני וכתוצאה מכך איבד צה״ל שטחי אש רבים. \n \n כתחליף לשטחי סיני החל שימוש צבא באזור הנגב הדרומי לטובת אימונים. \n \n בתמורה להסכם השלום המשותף בנו האמריקאים 5 בסיסי הכשרה באזור ביניהם סיירים."
  },
  {
    "expPageId": 2,
    "headline": "סק״ג סיירים",
    "text": "בקעה גדולה באזור הניקוז של נחל חיון, \n אורכה כ-6 ק״מ מתפרסת על שטח של 14 קמ״ר נמצאת בגובה של כ-600 מטר ומהווה פרוזדור טופוגרפי המפריד בין הרי תמנע למישורים הגדולים של הנחלים פארן וחיון."
  },
  {
    "expPageId": 3,
    "text": "גררו את המדינות השכנות בהתאם למפת ארץ ישראל"
  },
  {
    "expPageId": 4,
    "text": "גררו את גדודי חיל הגנת הגבולות על פי מיקומי התגים שלהם במפת ארץ ישראל"
  },
  {
    "answersForMap1": ["מצרים","סוריה", "לבנון", "עזה","יהודה ושומרון","ירדן"]
  },
  {
    "answersForMap2": ["גדוד \"שחף\" 869","גדוד \"ניצן\" 636","גדוד \"נשר\" 414","גדוד \"עיט\" 595","גדוד \"איתם\" 727","חטיבת הבקעה 417 \n אריות הירדן - 41 \n לביא הבקעה - 47","חטיבת פארן 512 \n קרקל - 33 \n ברדלס - 277"]
  }
]